ty_extensions/__init__.py
ty_extensions/__init__.pyi
ty_extensions/py.typed
ty_extensions_unofficial-0.1.0.dev6.dist-info/WHEEL
ty_extensions_unofficial-0.1.0.dev6.dist-info/METADATA
ty_extensions_unofficial-0.1.0.dev6.dist-info/RECORD
