Metadata-Version: 2.3
Name: ty-extensions-unofficial
Version: 0.1.0.dev6
Summary: A properly packaged fork of the official ty-extensions
Author: InSyncWithFoo
Author-email: InSyncWithFoo <insyncwithfoo@gmail.com>
Requires-Python: >=3.9
